raptorq-2.0.0.dist-info/METADATA
raptorq-2.0.0.dist-info/WHEEL
raptorq-2.0.0.dist-info/license_files/LICENSE
raptorq/__init__.py
raptorq/raptorq.abi3.so
raptorq-2.0.0.dist-info/RECORD
