Metadata-Version: 2.3
Name: raptorq
Version: 2.0.0
License-File: LICENSE
Summary: RaptorQ (RFC6330)
Home-Page: https://github.com/cberner/raptorq
Author: Christopher Berner <christopherberner@gmail.com>
Author-email: Christopher Berner <christopherberner@gmail.com>
License: Apache-2.0
Requires-Python: >=3.7
Project-URL: Source Code, https://github.com/cberner/raptorq
